cloudbeds_pms/__init__.py
cloudbeds_pms/api_client.py
cloudbeds_pms/api_response.py
cloudbeds_pms/configuration.py
cloudbeds_pms/exceptions.py
cloudbeds_pms/py.typed
cloudbeds_pms/rest.py
cloudbeds_pms/api/__init__.py
cloudbeds_pms/api/addons_api.py
cloudbeds_pms/api/applications_api.py
cloudbeds_pms/api/door_locks_api.py
cloudbeds_pms/api/events_api.py
cloudbeds_pms/api/housekeeping_api.py
cloudbeds_pms/api/integration_events_api.py
cloudbeds_pms/api/items_api.py
cloudbeds_pms/api/market_segmentation_api.py
cloudbeds_pms/api/property_api.py
cloudbeds_pms/api/reservations_api.py
cloudbeds_pms/api/rooms_api.py
cloudbeds_pms/models/__init__.py
cloudbeds_pms/models/addon_response_schema.py
cloudbeds_pms/models/addons_response_schema.py
cloudbeds_pms/models/age_group_response_schema.py
cloudbeds_pms/models/age_policy_create_request_schema.py
cloudbeds_pms/models/age_policy_create_request_schema_groups_inner.py
cloudbeds_pms/models/age_policy_patch_request_schema.py
cloudbeds_pms/models/age_policy_response_schema.py
cloudbeds_pms/models/age_policy_update_request_schema.py
cloudbeds_pms/models/age_policy_update_request_schema_groups_inner.py
cloudbeds_pms/models/allotment_block_auto_release_schedule_bulk_create_item_schema.py
cloudbeds_pms/models/allotment_block_auto_release_schedule_bulk_create_request_schema.py
cloudbeds_pms/models/allotment_block_auto_release_schedule_bulk_response_schema.py
cloudbeds_pms/models/allotment_block_auto_release_schedule_bulk_update_item_schema.py
cloudbeds_pms/models/allotment_block_auto_release_schedule_bulk_update_request_schema.py
cloudbeds_pms/models/allotment_block_auto_release_schedule_create_request_schema.py
cloudbeds_pms/models/allotment_block_auto_release_schedule_delete_request_schema.py
cloudbeds_pms/models/allotment_block_auto_release_schedule_list_request_schema.py
cloudbeds_pms/models/allotment_block_auto_release_schedule_list_response_schema.py
cloudbeds_pms/models/allotment_block_auto_release_schedule_response_schema.py
cloudbeds_pms-2.9.0.dist-info/licenses/LICENSE
cloudbeds_pms-2.9.0.dist-info/METADATA
cloudbeds_pms-2.9.0.dist-info/WHEEL
cloudbeds_pms-2.9.0.dist-info/top_level.txt
cloudbeds_pms-2.9.0.dist-info/RECORD
